{
    "title": "Power Supply Subsystem",
    "theme": "red",
    "startdate": null,
    "enddate": null,
    "dateprecision": "year",
    "desc": "",
    "icon": "",
    "icontitle": "",
    "keywords": [],
    "cat": "",
    "favicon": "",
    "headerids": true,
    "shownavbar": true,
    "content": {
        "content": {
            "type": "content",
            "boxed": false,
            "title": "",
            "theme": "",
            "fitscreen": false,
            "content": "power.md"
        }
    }
}